{
  "updatedAt": "2026-05-10T20:51:26.340Z",
  "source": "windsor.ai",
  "endpoint": "blended",
  "weeks": [
    {
      "weekStart": "2026-04-27",
      "costs": 1148.69
    },
    {
      "weekStart": "2026-05-04",
      "costs": 7414.39
    }
  ],
  "weeksBySource": {
    "2026-04-27": {
      "googleads": {
        "costs": 655.2998
      },
      "facebook": {
        "costs": 493.39
      }
    },
    "2026-05-04": {
      "googleads": {
        "costs": 5311.2096
      },
      "facebook": {
        "costs": 2103.18
      },
      "instagram": {}
    }
  },
  "sourcesDiscovered": [
    "facebook",
    "google_ads",
    "instagram",
    "intercom"
  ],
  "sourcesNormalized": [
    "facebook",
    "googleads",
    "instagram",
    "intercom"
  ],
  "sourcesMapped": [
    "facebook",
    "googleads",
    "instagram"
  ],
  "sourcesUnmapped": [
    "intercom"
  ],
  "fieldsBySource": {
    "googleads": {
      "account_name": "Join Brands - MA",
      "datasource": "google_ads",
      "date": "2026-05-03",
      "source": "google",
      "campaign": "TDD_Search_Brand_US",
      "spend": 224.6074
    },
    "facebook": {
      "account_name": "JoinBrands",
      "datasource": "facebook",
      "date": "2026-05-03",
      "source": "facebook",
      "campaign": "TDD - Remarketing - US - Onboarding Leads",
      "spend": 39.67
    },
    "intercom": {
      "account_name": "windsor",
      "datasource": "intercom",
      "date": "2026-05-03",
      "source": "intercom",
      "email": "mlee88374@gmail.com"
    },
    "instagram": {
      "account_name": "joinbrands_brands",
      "datasource": "instagram",
      "date": "2026-05-10",
      "followers_count": 1944,
      "source": "instagram"
    }
  },
  "sampleRowKeys": [
    "account_name",
    "datasource",
    "date",
    "followers_count",
    "source",
    "campaign",
    "spend",
    "email"
  ],
  "rowCount": 5858,
  "usableRowCount": 186
}
